visual_excel/__init__.py
visual_excel/__main__.py
visual_excel/py.typed
visual_excel-0.0.0.dist-info/entry_points.txt
visual_excel-0.0.0.dist-info/LICENSE
visual_excel-0.0.0.dist-info/WHEEL
visual_excel-0.0.0.dist-info/METADATA
visual_excel-0.0.0.dist-info/RECORD
