Metadata-Version: 2.1
Name: visual-excel
Version: 0.0.0
Summary: Visual Excel
Home-page: https://github.com/56kyle/visual-excel
License: MIT
Author: Kyle Oliver
Author-email: 56kyleoliver@gmail.com
Requires-Python: >=3.7,<4.0
Classifier: Development Status :: 1 - Planning
Classifier: License :: OSI Approved :: MIT License
Classifier: Programming Language :: Python :: 3
Classifier: Programming Language :: Python :: 3.10
Classifier: Programming Language :: Python :: 3.7
Classifier: Programming Language :: Python :: 3.8
Classifier: Programming Language :: Python :: 3.9
Requires-Dist: click (>=8.0.1)
Project-URL: Changelog, https://github.com/56kyle/visual-excel/releases
Project-URL: Documentation, https://visual-excel.readthedocs.io
Project-URL: Repository, https://github.com/56kyle/visual-excel
